adctoolbox/__init__.py
adctoolbox/cli.py
adctoolbox/aout/__init__.py
adctoolbox/aout/_fit_error_phase.py
adctoolbox/aout/_fit_sine_harmonics.py
adctoolbox/aout/_infer_signal_range.py
adctoolbox/aout/analyze_decomposition_polar.py
adctoolbox/aout/analyze_decomposition_time.py
adctoolbox/aout/analyze_error_autocorr.py
adctoolbox/aout/analyze_error_by_phase.py
adctoolbox/aout/analyze_error_by_value.py
adctoolbox/aout/analyze_error_envelope_spectrum.py
adctoolbox/aout/analyze_error_pdf.py
adctoolbox/aout/analyze_error_phase_plane.py
adctoolbox/aout/analyze_error_spectrum.py
adctoolbox/aout/analyze_inl_from_sine.py
adctoolbox/aout/analyze_phase_plane.py
adctoolbox/aout/compute_inl_from_sine.py
adctoolbox/aout/decompose_harmonic_error.py
adctoolbox/aout/fit_static_nonlin.py
adctoolbox/aout/plot_decomposition_polar.py
adctoolbox/aout/plot_decomposition_time.py
adctoolbox/aout/plot_dnl_inl.py
adctoolbox/aout/plot_rearranged_error_by_phase.py
adctoolbox/aout/plot_rearranged_error_by_value.py
adctoolbox/aout/rearrange_error_by_phase.py
adctoolbox/aout/rearrange_error_by_value.py
adctoolbox/calibration/__init__.py
adctoolbox/calibration/_estimate_frequencies.py
adctoolbox/calibration/_lstsq_solver.py
adctoolbox/calibration/_patch_rank_deficiency.py
adctoolbox/calibration/_post_process.py
adctoolbox/calibration/_prepare_input.py
adctoolbox/calibration/_scale_columns_for_conditioning.py
adctoolbox/calibration/calibrate_weight_sine.py
adctoolbox/calibration/calibrate_weight_sine_lite.py
adctoolbox/dout/__init__.py
adctoolbox/dout/analyze_bit_activity.py
adctoolbox/dout/analyze_enob_sweep.py
adctoolbox/dout/analyze_overflow.py
adctoolbox/dout/analyze_weight_radix.py
adctoolbox/examples/README.md
adctoolbox/examples/01_basic/exp_b01_environment_check.py
adctoolbox/examples/01_basic/exp_b02_coherent_vs_non_coherent.py
adctoolbox/examples/02_spectrum/exp_s01_analyze_spectrum_simplest.py
adctoolbox/examples/02_spectrum/exp_s02_analyze_spectrum_interactive.py
adctoolbox-0.5.0.dist-info/METADATA
adctoolbox-0.5.0.dist-info/WHEEL
adctoolbox-0.5.0.dist-info/entry_points.txt
adctoolbox-0.5.0.dist-info/top_level.txt
adctoolbox-0.5.0.dist-info/RECORD
