Metadata-Version: 2.4
Name: adctoolbox
Version: 0.5.0
Summary: ADC Testing and Analysis Toolkit
License: MIT
Requires-Python: >=3.10
Requires-Dist: numpy>=1.23.0
Requires-Dist: matplotlib>=3.6.0
Requires-Dist: scipy>=1.9.0
Provides-Extra: docs
Requires-Dist: sphinx>=7.0.0; extra == "docs"
Requires-Dist: sphinx-rtd-theme>=2.0.0; extra == "docs"
Requires-Dist: sphinx-autodoc-typehints>=1.24.0; extra == "docs"
Requires-Dist: myst-parser>=2.0.0; extra == "docs"
